[{"username":"sadra","password":"s","collection":["Simorgh","AllAttack","Iraj","Bahman","WisdomCrown"],"allDecks":{"1":["Simorgh","AllAttack","AllAttack","AllAttack","AllAttack","AllAttack","Bahman","Bahman","Bahman","Bahman","Iraj","Iraj","Iraj","Iraj","Iraj","Iraj","Iraj","Iraj","Iraj","WisdomCrown"]},"matchHistory":[],"mainDeck":"1","daric":3250},{"username":"alireza","password":"a","collection":["Rostam","Iraj","WisdomCrown"],"allDecks":{"1":["Rostam","Iraj","Iraj","Iraj","Iraj","Eagle","Eagle","Eagle","Eagle","Eagle","Siavash","Siavash","Siavash","Siavash","Siavash","Siavash","Siavash","Siavash","Siavash","WisdomCrown"]},"matchHistory":[],"mainDeck":"1","daric":1000000}]